{
  "id": "220f5855-fb41-4c18-ad34-0b7e58573705",
  "prevId": "b5946639-7431-4607-9894-99b02eb45aa8",
  "version": "5",
  "dialect": "pg",
  "tables": {
    "apikeys": {
      "name": "apikeys",
      "schema": "",
      "columns": {
        "id": {
          "name": "id",
          "type": "varchar",
          "primaryKey": true,
          "notNull": true
        },
        "label": {
          "name": "label",
          "type": "varchar",
          "primaryKey": false,
          "notNull": true
        },
        "key": {
          "name": "key",
          "type": "varchar",
          "primaryKey": false,
          "notNull": true
        },
        "integrationId": {
          "name": "integrationId",
          "type": "varchar",
          "primaryKey": false,
          "notNull": true
        },
        "authorId": {
          "name": "authorId",
          "type": "varchar",
          "primaryKey": false,
          "notNull": true
        }
      },
      "indexes": {},
      "foreignKeys": {},
      "compositePrimaryKeys": {},
      "uniqueConstraints": {}
    },
    "drafts": {
      "name": "drafts",
      "schema": "",
      "columns": {
        "id": {
          "name": "id",
          "type": "varchar",
          "primaryKey": true,
          "notNull": true
        },
        "title": {
          "name": "title",
          "type": "varchar",
          "primaryKey": false,
          "notNull": true
        },
        "dateCreated": {
          "name": "dateCreated",
          "type": "timestamp",
          "primaryKey": false,
          "notNull": false,
          "default": "now()"
        },
        "dateUpdated": {
          "name": "dateUpdated",
          "type": "timestamp",
          "primaryKey": false,
          "notNull": false
        },
        "order": {
          "name": "order",
          "type": "integer",
          "primaryKey": false,
          "notNull": false
        },
        "projectId": {
          "name": "projectId",
          "type": "varchar",
          "primaryKey": false,
          "notNull": false
        },
        "authorId": {
          "name": "authorId",
          "type": "varchar",
          "primaryKey": false,
          "notNull": true
        }
      },
      "indexes": {},
      "foreignKeys": {},
      "compositePrimaryKeys": {},
      "uniqueConstraints": {}
    },
    "project": {
      "name": "project",
      "schema": "",
      "columns": {
        "id": {
          "name": "id",
          "type": "varchar",
          "primaryKey": true,
          "notNull": true
        },
        "title": {
          "name": "title",
          "type": "varchar",
          "primaryKey": false,
          "notNull": false
        },
        "color": {
          "name": "color",
          "type": "varchar",
          "primaryKey": false,
          "notNull": false
        },
        "order": {
          "name": "order",
          "type": "integer",
          "primaryKey": false,
          "notNull": false
        },
        "authorId": {
          "name": "authorId",
          "type": "varchar",
          "primaryKey": false,
          "notNull": true
        }
      },
      "indexes": {},
      "foreignKeys": {},
      "compositePrimaryKeys": {},
      "uniqueConstraints": {}
    },
    "task": {
      "name": "task",
      "schema": "",
      "columns": {
        "id": {
          "name": "id",
          "type": "varchar",
          "primaryKey": true,
          "notNull": true
        },
        "draftId": {
          "name": "draftId",
          "type": "varchar",
          "primaryKey": false,
          "notNull": false
        },
        "title": {
          "name": "title",
          "type": "varchar",
          "primaryKey": false,
          "notNull": false
        },
        "status": {
          "name": "status",
          "type": "varchar",
          "primaryKey": false,
          "notNull": false
        },
        "order": {
          "name": "order",
          "type": "integer",
          "primaryKey": false,
          "notNull": false
        },
        "dateCreated": {
          "name": "dateCreated",
          "type": "timestamp",
          "primaryKey": false,
          "notNull": false,
          "default": "now()"
        },
        "dateUpdated": {
          "name": "dateUpdated",
          "type": "timestamp",
          "primaryKey": false,
          "notNull": false
        },
        "dateCommitted": {
          "name": "dateCommitted",
          "type": "varchar",
          "primaryKey": false,
          "notNull": false
        },
        "dateCompleted": {
          "name": "dateCompleted",
          "type": "varchar",
          "primaryKey": false,
          "notNull": false
        },
        "dateTodo": {
          "name": "dateTodo",
          "type": "varchar",
          "primaryKey": false,
          "notNull": false
        },
        "projectId": {
          "name": "projectId",
          "type": "varchar",
          "primaryKey": false,
          "notNull": false
        },
        "authorId": {
          "name": "authorId",
          "type": "varchar",
          "primaryKey": false,
          "notNull": true
        }
      },
      "indexes": {},
      "foreignKeys": {},
      "compositePrimaryKeys": {},
      "uniqueConstraints": {}
    }
  },
  "enums": {},
  "schemas": {},
  "_meta": {
    "columns": {},
    "schemas": {},
    "tables": {}
  }
}